pca9570/__init__.py
pca9570/pca9570.py
pca9570-1.1.0.dist-info/LICENSE
pca9570-1.1.0.dist-info/METADATA
pca9570-1.1.0.dist-info/WHEEL
pca9570-1.1.0.dist-info/top_level.txt
pca9570-1.1.0.dist-info/RECORD
