Metadata-Version: 2.1
Name: pca9570
Version: 1.1.0
Summary: Support for the pca9570 pinmux
Home-page: https://github.com/matteoscordino/python-PCA9570-pinmux
Author: Matteo Scordino
License: UNKNOWN
Keywords: PCA9570
Platform: UNKNOWN
Classifier: Development Status :: 5 - Production/Stable
Classifier: License :: OSI Approved :: MIT License
Classifier: Programming Language :: Python :: 3
Classifier: Programming Language :: Python :: 3.6
Classifier: Programming Language :: Python :: 3.7
Classifier: Programming Language :: Python :: 3 :: Only
Requires-Python: >=3.6, <4
License-File: LICENSE
Requires-Dist: smbus
